rtl/hybrid_trading_core.sv
`timescale 1ns/1ps

module hybrid_trading_core (
    input wire clk,
    input wire rst_n,
    input wire [31:0] btc_price,
    input wire [31:0] eth_price,
    input wire market_data_valid,
    input wire [31:0] host_buy_limit,
    input wire [31:0] host_sell_limit,
    input wire [31:0] host_buy_qty,
    input wire [31:0] host_sell_qty,
    input wire [7:0] strategy_mode,
    input wire [15:0] strategy_params,
    input wire config_updated,
    output reg trade_trigger,
    output reg [31:0] trade_price,
    output reg [31:0] trade_quantity,
    output reg trade_direction,
    output reg [7:0] trade_reason
);

wire builtin_trade_signal = (btc_price > (eth_price * strategy_params[15:0]));
wire host_buy_trigger = (strategy_mode[0] && market_data_valid && (btc_price <= host_buy_limit));
wire host_sell_trigger = (strategy_mode[1] && market_data_valid && (btc_price >= host_sell_limit));

always @(posedge clk or negedge rst_n) begin
    if (!rst_n) begin
        trade_trigger <= 1'b0;
        trade_price <= 32'h0;
        trade_quantity <= 32'h1;
        trade_direction <= 1'b0;
        trade_reason <= 8'h00;
    end else if (market_data_valid) begin
        if (host_buy_trigger) begin
            trade_trigger <= 1'b1;
            trade_price <= btc_price;
            trade_quantity <= host_buy_qty;
            trade_direction <= 1'b0;
            trade_reason <= 8'h10;
        end else if (host_sell_trigger) begin
            trade_trigger <= 1'b1;
            trade_price <= btc_price;
            trade_quantity <= host_sell_qty;
            trade_direction <= 1'b1;
            trade_reason <= 8'h20;
        end else if ((strategy_mode == 8'h00) && builtin_trade_signal) begin
            trade_trigger <= 1'b1;
            trade_price <= eth_price;
            trade_quantity <= 32'h1;
            trade_direction <= 1'b0;
            trade_reason <= 8'h01;
        end else begin
            trade_trigger <= 1'b0;
        end
    end else begin
        trade_trigger <= 1'b0;
    end
end

endmodule

rtl/spi_interface.sv
`timescale 1ns/1ps

module spi_interface (
    input wire clk,
    input wire rst_n,
    input wire spi_sclk,
    input wire spi_mosi,
    output reg spi_miso,
    input wire spi_cs_n,
    output reg [31:0] buy_price_limit,
    output reg [31:0] sell_price_limit,  
    output reg [31:0] buy_quantity,
    output reg [31:0] sell_quantity,
    output reg [7:0] strategy_mode,
    output reg [15:0] strategy_params,
    output reg config_updated
);

reg [4:0] bit_counter;
reg [7:0] spi_addr;
reg [31:0] shift_register;

always @(posedge spi_sclk or negedge rst_n) begin
    if (!rst_n) begin
        bit_counter <= 5'd0;
        shift_register <= 32'h0;
    end else if (!spi_cs_n) begin
        shift_register <= {shift_register[30:0], spi_mosi};
        bit_counter <= bit_counter + 1;
        if (bit_counter == 5'd7) begin
            spi_addr <= shift_register[7:0];
        end
    end
end

always @(posedge clk or negedge rst_n) begin
    if (!rst_n) begin
        buy_price_limit <= 32'h0000_A8C0;
        sell_price_limit <= 32'h0000_AF00;
        buy_quantity <= 32'h0000_0001;
        sell_quantity <= 32'h0000_0001;
        strategy_mode <= 8'h00;
        strategy_params <= 16'h0010;
        config_updated <= 1'b0;
    end else begin
        config_updated <= 1'b0;
        if (!spi_cs_n && bit_counter == 5'd31) begin
            case (spi_addr)
                8'h00: begin buy_price_limit <= shift_register; config_updated <= 1'b1; end
                8'h01: begin sell_price_limit <= shift_register; config_updated <= 1'b1; end
                8'h02: begin buy_quantity <= shift_register; config_updated <= 1'b1; end
                8'h03: begin sell_quantity <= shift_register; config_updated <= 1'b1; end
                8'h04: begin strategy_mode <= shift_register[7:0]; config_updated <= 1'b1; end
                8'h05: begin strategy_params <= shift_register[15:0]; config_updated <= 1'b1; end
            endcase
        end
    end
end

endmodule

rtl/hft_asic_complete.sv
`timescale 1ns/1ps

module hft_asic_complete (
    input wire clk,
    input wire rst_n,
    input wire spi_sclk,
    input wire spi_mosi,
    output wire spi_miso,
    input wire spi_cs_n,
    input wire [63:0] market_data,
    input wire market_valid,
    output wire [63:0] trade_order,
    output wire trade_valid,
    output wire trade_buy_sell,
    output wire [7:0] execution_reason
);

wire [31:0] spi_buy_limit, spi_sell_limit, spi_buy_qty, spi_sell_qty;
wire [7:0] spi_strategy_mode;
wire [15:0] spi_strategy_params;
wire spi_config_updated;
wire [31:0] current_btc_price = market_data[63:32];
wire [31:0] current_eth_price = market_data[31:0];
wire trade_triggered;
wire [31:0] trade_price, trade_quantity;
wire trade_direction;
wire [7:0] trade_reason;

spi_interface spi_ctrl (
    .clk(clk), .rst_n(rst_n), .spi_sclk(spi_sclk), .spi_mosi(spi_mosi), 
    .spi_miso(spi_miso), .spi_cs_n(spi_cs_n), .buy_price_limit(spi_buy_limit),
    .sell_price_limit(spi_sell_limit), .buy_quantity(spi_buy_qty),
    .sell_quantity(spi_sell_qty), .strategy_mode(spi_strategy_mode),
    .strategy_params(spi_strategy_params), .config_updated(spi_config_updated)
);

hybrid_trading_core trading_engine (
    .clk(clk), .rst_n(rst_n), .btc_price(current_btc_price), .eth_price(current_eth_price),
    .market_data_valid(market_valid), .host_buy_limit(spi_buy_limit),
    .host_sell_limit(spi_sell_limit), .host_buy_qty(spi_buy_qty),
    .host_sell_qty(spi_sell_qty), .strategy_mode(spi_strategy_mode),
    .strategy_params(spi_strategy_params), .config_updated(spi_config_updated),
    .trade_trigger(trade_triggered), .trade_price(trade_price),
    .trade_quantity(trade_quantity), .trade_direction(trade_direction),
    .trade_reason(trade_reason)
);

assign trade_order = {trade_price, trade_quantity};
assign trade_valid = trade_triggered;
assign trade_buy_sell = trade_direction;
assign execution_reason = trade_reason;

endmodule

verification/complete_system_tb.sv
`timescale 1ns/1ps

module dynamic_complete_system_tb;
    reg clk, rst_n;
    reg spi_sclk, spi_mosi, spi_cs_n;
    wire spi_miso;
    reg [63:0] market_data;
    reg market_valid;
    wire [63:0] trade_order;
    wire trade_valid;
    wire trade_buy_sell;
    wire [7:0] execution_reason;

    // Instantiate complete system
    hft_asic_complete dut (
        .clk(clk), .rst_n(rst_n),
        .spi_sclk(spi_sclk), .spi_mosi(spi_mosi), .spi_miso(spi_miso), .spi_cs_n(spi_cs_n),
        .market_data(market_data), .market_valid(market_valid),
        .trade_order(trade_order), .trade_valid(trade_valid),
        .trade_buy_sell(trade_buy_sell), .execution_reason(execution_reason)
    );

    // Clock generation
    initial clk = 0;
    always #0.5 clk = ~clk;  // 1GHz
    
    initial spi_sclk = 0;
    always #5 spi_sclk = ~spi_sclk;  // 100MHz SPI

    // VCD generation
    initial begin
        $dumpfile("dynamic_complete_system.vcd");
        $dumpvars(0, dynamic_complete_system_tb);
    end

    // Variables for dynamic price generation
    integer btc_price, eth_price;
    
    // Dynamic Market Data & SPI Control
    initial begin
        $display("=== DYNAMIC HFT ASIC DEMONSTRATION ===");
        rst_n = 0; spi_cs_n = 1; market_valid = 0; spi_mosi = 0;
        btc_price = 43000; eth_price = 2600;
        #20; rst_n = 1;

        // Run concurrent processes
        fork
            // Process 1: Dynamic Market Data
            begin
                repeat(20) begin
                    // Vary BTC price ±$2000, ETH price ±$200
                    btc_price = 43000 + ($random % 4000) - 2000;
                    eth_price = 2600 + ($random % 400) - 200;
                    market_data = {btc_price[31:0], eth_price[31:0]};
                    market_valid = 1;
                    $display("[%0t] Market Update: BTC=$%0d, ETH=$%0d", $time, btc_price, eth_price);
                    #20;
                    market_valid = 0;
                    #20;
                end
            end
            
            // Process 2: SPI Host Commands
            begin
                #50; // Wait for system to stabilize
                $display("[%0t] Host Setting Buy Order: $42,500 for 3 units", $time);
                spi_write(8'h00, 32'd42500); // Buy limit
                spi_write(8'h02, 32'd3);     // Quantity
                spi_write(8'h04, 8'h01);     // Host buy mode
                
                #200;
                $display("[%0t] Host Setting Sell Order: $45,000 for 2 units", $time);
                spi_write(8'h01, 32'd45000); // Sell limit
                spi_write(8'h03, 32'd2);     // Quantity
                spi_write(8'h04, 8'h02);     // Host sell mode
                
                #200;
                $display("[%0t] Host Enabling Built-in Strategy", $time);
                spi_write(8'h05, 16'd18);    // Multiplier = 18
                spi_write(8'h04, 8'h00);     // Built-in mode
            end
        join

        #100;
        $display("=== DYNAMIC SIMULATION COMPLETE ===");
        $finish;
    end

    // SPI Write Task (Improved)
    task spi_write(input [7:0] addr, input [31:0] data);
        integer i;
        begin
            $display("  SPI Write: Addr=0x%02X, Data=0x%08X", addr, data);
            spi_cs_n = 0;
            #10;
            
            // Send address byte
            for (i = 7; i >= 0; i = i - 1) begin
                spi_mosi = addr[i];
                @(posedge spi_sclk);
            end
            
            // Send data (32 bits)
            for (i = 31; i >= 0; i = i - 1) begin
                spi_mosi = data[i];
                @(posedge spi_sclk);
            end
            
            spi_cs_n = 1;
            #20;
        end
    endtask

    // Enhanced Trade Monitoring
    always @(posedge clk) begin
        if (trade_valid) begin
            case (execution_reason)
                8'h01: $display("  🤖 BUILT-IN ARBITRAGE: %s $%0d Qty:%0d", 
                               trade_buy_sell ? "SELL" : "BUY", 
                               trade_order[63:32], trade_order[31:0]);
                8'h10: $display("  💰 HOST BUY ORDER: $%0d Qty:%0d", 
                               trade_order[63:32], trade_order[31:0]);
                8'h20: $display("  💸 HOST SELL ORDER: $%0d Qty:%0d", 
                               trade_order[63:32], trade_order[31:0]);
                default: $display("  ❓ UNKNOWN TRADE: Reason=%02h", execution_reason);
            endcase
        end
    end

    // Price Analysis Display
    always @(posedge market_valid) begin
        #1; // Small delay for clean display
        if (btc_price > (eth_price * 16))
            $display("    ✅ Arbitrage Opportunity: %0d > %0d", btc_price, eth_price * 16);
        else
            $display("    ❌ No Arbitrage: %0d ≤ %0d", btc_price, eth_price * 16);
    end

endmodule

results/dynamic_complete_system.vcd
$date
	Tue Aug 26 19:52:34 2025
$end
$version
	Icarus Verilog
$end
$timescale
	1ps
$end
$scope module dynamic_complete_system_tb $end
$var wire 1 ! trade_valid $end
$var wire 64 " trade_order [63:0] $end
$var wire 1 # trade_buy_sell $end
$var wire 1 $ spi_miso $end
$var wire 8 % execution_reason [7:0] $end
$var reg 1 & clk $end
$var reg 64 ' market_data [63:0] $end
$var reg 1 ( market_valid $end
$var reg 1 ) rst_n $end
$var reg 1 * spi_cs_n $end
$var reg 1 + spi_mosi $end
$var reg 1 , spi_sclk $end
$var integer 32 - btc_price [31:0] $end
$var integer 32 . eth_price [31:0] $end
$scope module dut $end
$var wire 1 & clk $end
$var wire 8 / execution_reason [7:0] $end
$var wire 64 0 market_data [63:0] $end
$var wire 1 ( market_valid $end
$var wire 1 ) rst_n $end
$var wire 1 * spi_cs_n $end
$var wire 1 + spi_mosi $end
$var wire 1 , spi_sclk $end
$var wire 1 # trade_buy_sell $end
$var wire 1 ! trade_valid $end
$var wire 1 1 trade_triggered $end
$var wire 8 2 trade_reason [7:0] $end
$var wire 32 3 trade_quantity [31:0] $end
$var wire 32 4 trade_price [31:0] $end
$var wire 64 5 trade_order [63:0] $end
$var wire 1 6 trade_direction $end
$var wire 16 7 spi_strategy_params [15:0] $end
$var wire 8 8 spi_strategy_mode [7:0] $end
$var wire 32 9 spi_sell_qty [31:0] $end
$var wire 32 : spi_sell_limit [31:0] $end
$var wire 1 $ spi_miso $end
$var wire 1 ; spi_config_updated $end
$var wire 32 < spi_buy_qty [31:0] $end
$var wire 32 = spi_buy_limit [31:0] $end
$var wire 32 > current_eth_price [31:0] $end
$var wire 32 ? current_btc_price [31:0] $end
$scope module spi_ctrl $end
$var wire 1 & clk $end
$var wire 1 ) rst_n $end
$var wire 1 * spi_cs_n $end
$var wire 1 + spi_mosi $end
$var wire 1 , spi_sclk $end
$var reg 5 @ bit_counter [4:0] $end
$var reg 32 A buy_price_limit [31:0] $end
$var reg 32 B buy_quantity [31:0] $end
$var reg 1 ; config_updated $end
$var reg 32 C sell_price_limit [31:0] $end
$var reg 32 D sell_quantity [31:0] $end
$var reg 32 E shift_register [31:0] $end
$var reg 8 F spi_addr [7:0] $end
$var reg 1 $ spi_miso $end
$var reg 8 G strategy_mode [7:0] $end
$var reg 16 H strategy_params [15:0] $end
$upscope $end
$scope module trading_engine $end
$var wire 32 I btc_price [31:0] $end
$var wire 1 & clk $end
$var wire 1 ; config_updated $end
$var wire 32 J eth_price [31:0] $end
$var wire 32 K host_buy_limit [31:0] $end
$var wire 32 L host_buy_qty [31:0] $end
$var wire 1 M host_buy_trigger $end
$var wire 32 N host_sell_limit [31:0] $end
$var wire 32 O host_sell_qty [31:0] $end
$var wire 1 P host_sell_trigger $end
$var wire 1 ( market_data_valid $end
$var wire 1 ) rst_n $end
$var wire 8 Q strategy_mode [7:0] $end
$var wire 16 R strategy_params [15:0] $end
$var wire 1 S builtin_trade_signal $end
$var reg 1 6 trade_direction $end
$var reg 32 T trade_price [31:0] $end
$var reg 32 U trade_quantity [31:0] $end
$var reg 8 V trade_reason [7:0] $end
$var reg 1 1 trade_trigger $end
$upscope $end
$upscope $end
$scope task spi_write $end
$var reg 8 W addr [7:0] $end
$var reg 32 X data [31:0] $end
$var integer 32 Y i [31:0] $end
$upscope $end
$upscope $end
$enddefinitions $end
#0
$dumpvars
bx Y
bx X
bx W
b0 V
b1 U
b0 T
xS
b10000 R
b0 Q
0P
b1 O
b1010111100000000 N
0M
b1 L
b1010100011000000 K
bx J
bx I
b10000 H
b0 G
bx F
b0 E
b1 D
b1010111100000000 C
b1 B
b1010100011000000 A
b0 @
bx ?
bx >
b1010100011000000 =
b1 <
0;
b1010111100000000 :
b1 9
b0 8
b10000 7
06
b1 5
b0 4
b1 3
b0 2
01
bx 0
b0 /
b101000101000 .
b1010011111111000 -
0,
0+
1*
0)
0(
bx '
0&
b0 %
x$
0#
b1 "
0!
$end
#500
1&
#1000
0&
#1500
1&
#2000
0&
#2500
1&
#3000
0&
#3500
1&
#4000
0&
#4500
1&
#5000
0&
1,
#5500
1&
#6000
0&
#6500
1&
#7000
0&
#7500
1&
#8000
0&
#8500
1&
#9000
0&
#9500
1&
#10000
0&
0,
#10500
1&
#11000
0&
#11500
1&
#12000
0&
#12500
1&
#13000
0&
#13500
1&
#14000
0&
#14500
1&
#15000
0&
1,
#15500
1&
#16000
0&
#16500
1&
#17000
0&
#17500
1&
#18000
0&
#18500
1&
#19000
0&
#19500
1&
#20000
1S
b1010111011001100 ?
b1010111011001100 I
b11111010001 >
b11111010001 J
0&
0,
1(
b101011101100110000000000000000000000011111010001 '
b101011101100110000000000000000000000011111010001 0
b11111010001 .
b1010111011001100 -
1)
#20500
b1 %
b1 /
b1 2
b1 V
b1111101000100000000000000000000000000000001 "
b1111101000100000000000000000000000000000001 5
b11111010001 4
b11111010001 T
1!
11
1&
#21000
0&
#21500
1&
#22000
0&
#22500
1&
#23000
0&
#23500
1&
#24000
0&
#24500
1&
#25000
0&
1,
#25500
1&
#26000
0&
#26500
1&
#27000
0&
#27500
1&
#28000
0&
#28500
1&
#29000
0&
#29500
1&
#30000
0&
0,
#30500
1&
#31000
0&
#31500
1&
#32000
0&
#32500
1&
#33000
0&
#33500
1&
#34000
0&
#34500
1&
#35000
0&
1,
#35500
1&
#36000
0&
#36500
1&
#37000
0&
#37500
1&
#38000
0&
#38500
1&
#39000
0&
#39500
1&
#40000
0&
0,
0(
#40500
0!
01
1&
#41000
0&
#41500
1&
#42000
0&
#42500
1&
#43000
0&
#43500
1&
#44000
0&
#44500
1&
#45000
0&
1,
#45500
1&
#46000
0&
#46500
1&
#47000
0&
#47500
1&
#48000
0&
#48500
1&
#49000
0&
#49500
1&
#50000
0&
0,
#50500
1&
#51000
0&
#51500
1&
#52000
0&
#52500
1&
#53000
0&
#53500
1&
#54000
0&
#54500
1&
#55000
0&
1,
#55500
1&
#56000
0&
#56500
1&
#57000
0&
#57500
1&
#58000
0&
#58500
1&
#59000
0&
#59500
1&
#60000
b1001101101010001 ?
b1001101101010001 I
b100011110011 >
b100011110011 J
0&
0,
1(
b100110110101000100000000000000000000100011110011 '
b100110110101000100000000000000000000100011110011 0
b100011110011 .
b1001101101010001 -
#60500
b10001111001100000000000000000000000000000001 "
b10001111001100000000000000000000000000000001 5
b100011110011 4
b100011110011 T
1!
11
1&
#61000
0&
#61500
1&
#62000
0&
#62500
1&
#63000
0&
#63500
1&
#64000
0&
#64500
1&
#65000
0&
1,
#65500
1&
#66000
0&
#66500
1&
#67000
0&
#67500
1&
#68000
0&
#68500
1&
#69000
0&
#69500
1&
#70000
0&
0,
0*
b1010011000000100 X
b0 W
#70500
1&
#71000
0&
#71500
1&
#72000
0&
#72500
1&
#73000
0&
#73500
1&
#74000
0&
#74500
1&
#75000
b1 @
0&
1,
#75500
1&
#76000
0&
#76500
1&
#77000
0&
#77500
1&
#78000
0&
#78500
1&
#79000
0&
#79500
1&
#80000
0&
0,
b111 Y
0(
#80500
0!
01
1&
#81000
0&
#81500
1&
#82000
0&
#82500
1&
#83000
0&
#83500
1&
#84000
0&
#84500
1&
#85000
b10 @
b110 Y
0&
1,
#85500
1&
#86000
0&
#86500
1&
#87000
0&
#87500
1&
#88000
0&
#88500
1&
#89000
0&
#89500
1&
#90000
0&
0,
#90500
1&
#91000
0&
#91500
1&
#92000
0&
#92500
1&
#93000
0&
#93500
1&
#94000
0&
#94500
1&
#95000
b11 @
b101 Y
0&
1,
#95500
1&
#96000
0&
#96500
1&
#97000
0&
#97500
1&
#98000
0&
#98500
1&
#99000
0&
#99500
1&
#100000
b1010101110110101 ?
b1010101110110101 I
1S
b100111111101 >
b100111111101 J
0&
0,
1(
b101010111011010100000000000000000000100111111101 '
b101010111011010100000000000000000000100111111101 0
b100111111101 .
b1010101110110101 -
#100500
b10011111110100000000000000000000000000000001 "
b10011111110100000000000000000000000000000001 5
b100111111101 4
b100111111101 T
1!
11
1&
#101000
0&
#101500
1&
#102000
0&
#102500
1&
#103000
0&
#103500
1&
#104000
0&
#104500
1&
#105000
b100 @
b100 Y
0&
1,
#105500
1&
#106000
0&
#106500
1&
#107000
0&
#107500
1&
#108000
0&
#108500
1&
#109000
0&
#109500
1&
#110000
0&
0,
#110500
1&
#111000
0&
#111500
1&
#112000
0&
#112500
1&
#113000
0&
#113500
1&
#114000
0&
#114500
1&
#115000
b101 @
b11 Y
0&
1,
#115500
1&
#116000
0&
#116500
1&
#117000
0&
#117500
1&
#118000
0&
#118500
1&
#119000
0&
#119500
1&
#120000
0&
0,
0(
#120500
0!
01
1&
#121000
0&
#121500
1&
#122000
0&
#122500
1&
#123000
0&
#123500
1&
#124000
0&
#124500
1&
#125000
b110 @
b10 Y
0&
1,
#125500
1&
#126000
0&
#126500
1&
#127000
0&
#127500
1&
#128000
0&
#128500
1&
#129000
0&
#129500
1&
#130000
0&
0,
#130500
1&
#131000
0&
#131500
1&
#132000
0&
#132500
1&
#133000
0&
#133500
1&
#134000
0&
#134500
1&
#135000
b111 @
b1 Y
0&
1,
#135500
1&
#136000
0&
#136500
1&
#137000
0&
#137500
1&
#138000
0&
#138500
1&
#139000
0&
#139500
1&
#140000
0S
b1001010010001101 ?
b1001010010001101 I
b100101010010 >
b100101010010 J
0&
0,
1(
b100101001000110100000000000000000000100101010010 '
b100101001000110100000000000000000000100101010010 0
b100101010010 .
b1001010010001101 -
#140500
1&
#141000
0&
#141500
1&
#142000
0&
#142500
1&
#143000
0&
#143500
1&
#144000
0&
#144500
1&
#145000
b0 F
b1000 @
b0 Y
0&
1,
#145500
1&
#146000
0&
#146500
1&
#147000
0&
#147500
1&
#148000
0&
#148500
1&
#149000
0&
#149500
1&
#150000
0&
0,
#150500
1&
#151000
0&
#151500
1&
#152000
0&
#152500
1&
#153000
0&
#153500
1&
#154000
0&
#154500
1&
#155000
b1001 @
b11111 Y
0&
1,
#155500
1&
#156000
0&
#156500
1&
#157000
0&
#157500
1&
#158000
0&
#158500
1&
#159000
0&
#159500
1&
#160000
0&
0,
0(
#160500
1&
#161000
0&
#161500
1&
#162000
0&
#162500
1&
#163000
0&
#163500
1&
#164000
0&
#164500
1&
#165000
b1010 @
b11110 Y
0&
1,
#165500
1&
#166000
0&
#166500
1&
#167000
0&
#167500
1&
#168000
0&
#168500
1&
#169000
0&
#169500
1&
#170000
0&
0,
#170500
1&
#171000
0&
#171500
1&
#172000
0&
#172500
1&
#173000
0&
#173500
1&
#174000
0&
#174500
1&
#175000
b1011 @
b11101 Y
0&
1,
#175500
1&
#176000
0&
#176500
1&
#177000
0&
#177500
1&
#178000
0&
#178500
1&
#179000
0&
#179500
1&
#180000
1S
b1010110101001001 ?
b1010110101001001 I
b100101111101 >
b100101111101 J
0&
0,
1(
b101011010100100100000000000000000000100101111101 '
b101011010100100100000000000000000000100101111101 0
b100101111101 .
b1010110101001001 -
#180500
b10010111110100000000000000000000000000000001 "
b10010111110100000000000000000000000000000001 5
b100101111101 4
b100101111101 T
1!
11
1&
#181000
0&
#181500
1&
#182000
0&
#182500
1&
#183000
0&
#183500
1&
#184000
0&
#184500
1&
#185000
b1100 @
b11100 Y
0&
1,
#185500
1&
#186000
0&
#186500
1&
#187000
0&
#187500
1&
#188000
0&
#188500
1&
#189000
0&
#189500
1&
#190000
0&
0,
#190500
1&
#191000
0&
#191500
1&
#192000
0&
#192500
1&
#193000
0&
#193500
1&
#194000
0&
#194500
1&
#195000
b1101 @
b11011 Y
0&
1,
#195500
1&
#196000
0&
#196500
1&
#197000
0&
#197500
1&
#198000
0&
#198500
1&
#199000
0&
#199500
1&
#200000
0&
0,
0(
#200500
0!
01
1&
#201000
0&
#201500
1&
#202000
0&
#202500
1&
#203000
0&
#203500
1&
#204000
0&
#204500
1&
#205000
b1110 @
b11010 Y
0&
1,
#205500
1&
#206000
0&
#206500
1&
#207000
0&
#207500
1&
#208000
0&
#208500
1&
#209000
0&
#209500
1&
#210000
0&
0,
#210500
1&
#211000
0&
#211500
1&
#212000
0&
#212500
1&
#213000
0&
#213500
1&
#214000
0&
#214500
1&
#215000
b1111 @
b11001 Y
0&
1,
#215500
1&
#216000
0&
#216500
1&
#217000
0&
#217500
1&
#218000
0&
#218500
1&
#219000
0&
#219500
1&
#220000
b1010110100011110 ?
b1010110100011110 I
0S
b101011101101 >
b101011101101 J
0&
0,
1(
b101011010001111000000000000000000000101011101101 '
b101011010001111000000000000000000000101011101101 0
b101011101101 .
b1010110100011110 -
#220500
1&
#221000
0&
#221500
1&
#222000
0&
#222500
1&
#223000
0&
#223500
1&
#224000
0&
#224500
1&
#225000
b10000 @
b11000 Y
0&
1,
#225500
1&
#226000
0&
#226500
1&
#227000
0&
#227500
1&
#228000
0&
#228500
1&
#229000
0&
#229500
1&
#230000
0&
0,
#230500
1&
#231000
0&
#231500
1&
#232000
0&
#232500
1&
#233000
0&
#233500
1&
#234000
0&
#234500
1&
#235000
b10001 @
b10111 Y
0&
1,
#235500
1&
#236000
0&
#236500
1&
#237000
0&
#237500
1&
#238000
0&
#238500
1&
#239000
0&
#239500
1&
#240000
0&
0,
0(
#240500
1&
#241000
0&
#241500
1&
#242000
0&
#242500
1&
#243000
0&
#243500
1&
#244000
0&
#244500
1&
#245000
b10010 @
b10110 Y
0&
1,
#245500
1&
#246000
0&
#246500
1&
#247000
0&
#247500
1&
#248000
0&
#248500
1&
#249000
0&
#249500
1&
#250000
0&
0,
#250500
1&
#251000
0&
#251500
1&
#252000
0&
#252500
1&
#253000
0&
#253500
1&
#254000
0&
#254500
1&
#255000
b10011 @
b10101 Y
0&
1,
#255500
1&
#256000
0&
#256500
1&
#257000
0&
#257500
1&
#258000
0&
#258500
1&
#259000
0&
#259500
1&
#260000
b1010111001010101 ?
b1010111001010101 I
1S
b100101101100 >
b100101101100 J
0&
0,
1(
b101011100101010100000000000000000000100101101100 '
b101011100101010100000000000000000000100101101100 0
b100101101100 .
b1010111001010101 -
#260500
b10010110110000000000000000000000000000000001 "
b10010110110000000000000000000000000000000001 5
b100101101100 4
b100101101100 T
1!
11
1&
#261000
0&
#261500
1&
#262000
0&
#262500
1&
#263000
0&
#263500
1&
#264000
0&
#264500
1&
#265000
b10100 @
b10100 Y
0&
1,
#265500
1&
#266000
0&
#266500
1&
#267000
0&
#267500
1&
#268000
0&
#268500
1&
#269000
0&
#269500
1&
#270000
0&
0,
#270500
1&
#271000
0&
#271500
1&
#272000
0&
#272500
1&
#273000
0&
#273500
1&
#274000
0&
#274500
1&
#275000
b10101 @
b10011 Y
0&
1,
#275500
1&
#276000
0&
#276500
1&
#277000
0&
#277500
1&
#278000
0&
#278500
1&
#279000
0&
#279500
1&
#280000
0&
0,
0(
#280500
0!
01
1&
#281000
0&
#281500
1&
#282000
0&
#282500
1&
#283000
0&
#283500
1&
#284000
0&
#284500
1&
#285000
b10110 @
b10010 Y
0&
1,
#285500
1&
#286000
0&
#286500
1&
#287000
0&
#287500
1&
#288000
0&
#288500
1&
#289000
0&
#289500
1&
#290000
0&
0,
#290500
1&
#291000
0&
#291500
1&
#292000
0&
#292500
1&
#293000
0&
#293500
1&
#294000
0&
#294500
1&
#295000
b10111 @
b10001 Y
0&
1,
#295500
1&
#296000
0&
#296500
1&
#297000
0&
#297500
1&
#298000
0&
#298500
1&
#299000
0&
#299500
1&
#300000
b1010110100000001 ?
b1010110100000001 I
b100010110110 >
b100010110110 J
0&
0,
1(
b101011010000000100000000000000000000100010110110 '
b101011010000000100000000000000000000100010110110 0
b100010110110 .
b1010110100000001 -
#300500
b10001011011000000000000000000000000000000001 "
b10001011011000000000000000000000000000000001 5
b100010110110 4
b100010110110 T
1!
11
1&
#301000
0&
#301500
1&
#302000
0&
#302500
1&
#303000
0&
#303500
1&
#304000
0&
#304500
1&
#305000
b11000 @
b10000 Y
0&
1,
#305500
1&
#306000
0&
#306500
1&
#307000
0&
#307500
1&
#308000
0&
#308500
1&
#309000
0&
#309500
1&
#310000
0&
0,
#310500
1&
#311000
0&
#311500
1&
#312000
0&
#312500
1&
#313000
0&
#313500
1&
#314000
0&
#314500
1&
#315000
b11001 @
b1 E
1+
b1111 Y
0&
1,
#315500
1&
#316000
0&
#316500
1&
#317000
0&
#317500
1&
#318000
0&
#318500
1&
#319000
0&
#319500
1&
#320000
0&
0,
0(
#320500
0!
01
1&
#321000
0&
#321500
1&
#322000
0&
#322500
1&
#323000
0&
#323500
1&
#324000
0&
#324500
1&
#325000
b11010 @
b10 E
0+
b1110 Y
0&
1,
#325500
1&
#326000
0&
#326500
1&
#327000
0&
#327500
1&
#328000
0&
#328500
1&
#329000
0&
#329500
1&
#330000
0&
0,
#330500
1&
#331000
0&
#331500
1&
#332000
0&
#332500
1&
#333000
0&
#333500
1&
#334000
0&
#334500
1&
#335000
b11011 @
b101 E
1+
b1101 Y
0&
1,
#335500
1&
#336000
0&
#336500
1&
#337000
0&
#337500
1&
#338000
0&
#338500
1&
#339000
0&
#339500
1&
#340000
b1001010000001101 ?
b1001010000001101 I
b11111101010 >
b11111101010 J
0&
0,
1(
b100101000000110100000000000000000000011111101010 '
b100101000000110100000000000000000000011111101010 0
b11111101010 .
b1001010000001101 -
#340500
b1111110101000000000000000000000000000000001 "
b1111110101000000000000000000000000000000001 5
b11111101010 4
b11111101010 T
1!
11
1&
#341000
0&
#341500
1&
#342000
0&
#342500
1&
#343000
0&
#343500
1&
#344000
0&
#344500
1&
#345000
b11100 @
b1010 E
0+
b1100 Y
0&
1,
#345500
1&
#346000
0&
#346500
1&
#347000
0&
#347500
1&
#348000
0&
#348500
1&
#349000
0&
#349500
1&
#350000
0&
0,
#350500
1&
#351000
0&
#351500
1&
#352000
0&
#352500
1&
#353000
0&
#353500
1&
#354000
0&
#354500
1&
#355000
b11101 @
b10100 E
b1011 Y
0&
1,
#355500
1&
#356000
0&
#356500
1&
#357000
0&
#357500
1&
#358000
0&
#358500
1&
#359000
0&
#359500
1&
#360000
0&
0,
0(
#360500
0!
01
1&
#361000
0&
#361500
1&
#362000
0&
#362500
1&
#363000
0&
#363500
1&
#364000
0&
#364500
1&
#365000
b11110 @
b101001 E
1+
b1010 Y
0&
1,
#365500
1&
#366000
0&
#366500
1&
#367000
0&
#367500
1&
#368000
0&
#368500
1&
#369000
0&
#369500
1&
#370000
0&
0,
#370500
1&
#371000
0&
#371500
1&
#372000
0&
#372500
1&
#373000
0&
#373500
1&
#374000
0&
#374500
1&
#375000
b11111 @
b1010011 E
b1001 Y
0&
1,
#375500
1;
b1010011 =
b1010011 A
b1010011 K
1&
#376000
0&
#376500
1;
1&
#377000
0&
#377500
1;
1&
#378000
0&
#378500
1;
1&
#379000
0&
#379500
1;
1&
#380000
b1010101101101101 ?
b1010101101101101 I
b100100110111 >
b100100110111 J
0&
0,
1(
b101010110110110100000000000000000000100100110111 '
b101010110110110100000000000000000000100100110111 0
b100100110111 .
b1010101101101101 -
#380500
b10010011011100000000000000000000000000000001 "
b10010011011100000000000000000000000000000001 5
b100100110111 4
b100100110111 T
1!
11
1;
1&
#381000
0&
#381500
1;
1&
#382000
0&
#382500
1;
1&
#383000
0&
#383500
1;
1&
#384000
0&
#384500
1;
1&
#385000
b0 @
b10100110 E
0+
b1000 Y
0&
1,
#385500
0;
1&
#386000
0&
#386500
1&
#387000
0&
#387500
1&
#388000
0&
#388500
1&
#389000
0&
#389500
1&
#390000
0&
0,
#390500
1&
#391000
0&
#391500
1&
#392000
0&
#392500
1&
#393000
0&
#393500
1&
#394000
0&
#394500
1&
#395000
b1 @
b101001100 E
b111 Y
0&
1,
#395500
1&
#396000
0&
#396500
1&
#397000
0&
#397500
1&
#398000
0&
#398500
1&
#399000
0&
#399500
1&
#400000
0&
0,
0(
#400500
0!
01
1&
#401000
0&
#401500
1&
#402000
0&
#402500
1&
#403000
0&
#403500
1&
#404000
0&
#404500
1&
#405000
b10 @
b1010011000 E
b110 Y
0&
1,
#405500
1&
#406000
0&
#406500
1&
#407000
0&
#407500
1&
#408000
0&
#408500
1&
#409000
0&
#409500
1&
#410000
0&
0,
#410500
1&
#411000
0&
#411500
1&
#412000
0&
#412500
1&
#413000
0&
#413500
1&
#414000
0&
#414500
1&
#415000
b11 @
b10100110000 E
b101 Y
0&
1,
